b_cfn_api_v2/__init__.py
b_cfn_api_v2/api.py
b_cfn_api_v2_test/integration/__init__.py
b_cfn_api_v2_test/integration/app.py
b_cfn_api_v2_test/integration/conftest.py
b_cfn_api_v2_test/integration/infra_create.py
b_cfn_api_v2_test/integration/infra_destroy.py
b_cfn_api_v2_test/integration/manager.py
b_cfn_api_v2_test/integration/fixtures/__init__.py
b_cfn_api_v2_test/integration/fixtures/access_token.py
b_cfn_api_v2_test/integration/fixtures/api_keys.py
b_cfn_api_v2_test/integration/infrastructure/__init__.py
b_cfn_api_v2_test/integration/infrastructure/api_stack.py
b_cfn_api_v2_test/integration/infrastructure/authorized_endpoint_api_key_stack.py
b_cfn_api_v2_test/integration/infrastructure/authorized_endpoint_user_pool_stack.py
b_cfn_api_v2_test/integration/infrastructure/main_stack.py
b_cfn_api_v2_test/integration/infrastructure/user_pool_stack.py
b_cfn_api_v2_test/integration/tests/__init__.py
b_cfn_api_v2_test/integration/tests/test_api_api_key_allow.py
b_cfn_api_v2_test/integration/tests/test_api_api_key_deny.py
b_cfn_api_v2_test/integration/tests/test_api_user_pool_allow.py
b_cfn_api_v2_test/integration/tests/test_api_user_pool_deny.py
b_cfn_api_v2-5.0.0.dist-info/LICENSE
b_cfn_api_v2-5.0.0.dist-info/METADATA
b_cfn_api_v2-5.0.0.dist-info/WHEEL
b_cfn_api_v2-5.0.0.dist-info/top_level.txt
b_cfn_api_v2-5.0.0.dist-info/RECORD
