Metadata-Version: 2.1
Name: b-cfn-api-v2
Version: 5.0.0
Summary: Convenient wrapper around CfnApi.
Home-page: https://github.com/biomapas/B.CfnApiV2.git
License: Apache License 2.0
Keywords: AWS API Gateway
Classifier: Programming Language :: Python :: 3
Classifier: Operating System :: OS Independent
License-File: LICENSE
Requires-Dist: b-cfn-custom-userpool-authorizer (<3.0.0,>=2.0.0)
Requires-Dist: b-cfn-custom-api-key-authorizer (<4.0.0,>=3.0.0)
Requires-Dist: aws-cdk-lib (<3.0.0,>=2.0.0)
Requires-Dist: aws-cdk-constructs (<3.0.0,>=2.0.0)
